broker_tools/__init__.py
broker_tools/configuration/__init__.py
broker_tools/configuration/kafka_settings.py
broker_tools/message_queue/__init__.py
broker_tools/message_queue/abstract_consumer.py
broker_tools/message_queue/abstract_producer.py
broker_tools/message_queue/kafka/Consumer.py
broker_tools/message_queue/kafka/Producer.py
broker_tools/message_queue/kafka/__init__.py
elyadata_mq-0.0.1.dist-info/METADATA
elyadata_mq-0.0.1.dist-info/WHEEL
elyadata_mq-0.0.1.dist-info/top_level.txt
elyadata_mq-0.0.1.dist-info/RECORD
