Metadata-Version: 2.1
Name: elyadata-mq
Version: 0.0.1
Summary: A kafka tools package that aims to facilitate using message queues
Author: Saifeddine ABIDI
Author-email: saifeddine.abidi@elyadata.com
Classifier: Programming Language :: Python :: 3
Classifier: Development Status :: 3 - Alpha
Classifier: Operating System :: OS Independent
Requires-Python: >=3.8
Requires-Dist: aiokafka (==0.7.2)
Requires-Dist: confluent-kafka (==1.7.0)
Requires-Dist: loguru
Requires-Dist: pydantic
Requires-Dist: typing-extensions (~=3.7.4)
